.long_description.md
MANIFEST.in
ReadMe.md
setup.cfg
setup.py
lib/yamlscript/__init__.py
lib/yamlscript.egg-info/PKG-INFO
lib/yamlscript.egg-info/SOURCES.txt
lib/yamlscript.egg-info/dependency_links.txt
lib/yamlscript.egg-info/requires.txt
lib/yamlscript.egg-info/top_level.txt
test/test.py